win_purge/__init__.py
win_purge/__main__.py
win_purge/directories.py
win_purge/registry.py
win_purge/reglib.py
win_purge-0.0.2.dist-info/METADATA
win_purge-0.0.2.dist-info/WHEEL
win_purge-0.0.2.dist-info/entry_points.txt
win_purge-0.0.2.dist-info/licenses/LICENSE.md
win_purge-0.0.2.dist-info/RECORD
