Metadata-Version: 2.4
Name: win-purge
Version: 0.0.2
Summary: Delete registry keys, registry value/ value_names, path entries, and often used installation directories based on a string search.
Project-URL: Homepage, https://github.com/Hazardous-Area/win_purge
Project-URL: Bug Tracker, https://github.com/Hazardous-Area/win_purge/issues
Author-email: James Parrott <james.parrott@proton.me>
License: Copyright (c) James Parrott 2024
License-File: LICENSE.md
Classifier: Operating System :: Microsoft :: Windows
Classifier: Programming Language :: Python :: 3
Requires-Python: >=3.9
Requires-Dist: send2trash
